sblpy/__init__.py
sblpy/client.py
sblpy/cog.py
sblpy/error.py
sblpy/http.py
sblpy/webhook/flask.py
sblpy/webhook/logger.py
sblpy/webhook/quart.py
SBL.py-0.1.0.dist-info/LICENSE
SBL.py-0.1.0.dist-info/METADATA
SBL.py-0.1.0.dist-info/WHEEL
SBL.py-0.1.0.dist-info/top_level.txt
SBL.py-0.1.0.dist-info/RECORD
